GreenletProfiler.py
MANIFEST.in
README.rst
setup.py
GreenletProfiler.egg-info/PKG-INFO
GreenletProfiler.egg-info/SOURCES.txt
GreenletProfiler.egg-info/dependency_links.txt
GreenletProfiler.egg-info/not-zip-safe
GreenletProfiler.egg-info/requires.txt
GreenletProfiler.egg-info/top_level.txt
_vendorized_yappi/__init__.py
_vendorized_yappi/_yappi.c
_vendorized_yappi/callstack.c
_vendorized_yappi/callstack.h
_vendorized_yappi/config.h
_vendorized_yappi/debug.h
_vendorized_yappi/freelist.c
_vendorized_yappi/freelist.h
_vendorized_yappi/hashtab.c
_vendorized_yappi/hashtab.h
_vendorized_yappi/mem.c
_vendorized_yappi/mem.h
_vendorized_yappi/timing.c
_vendorized_yappi/timing.h
_vendorized_yappi/yappi.py
test/test_greenlet_profiler.py