Metadata-Version: 1.0
Name: GreenletProfiler
Version: 0.1
Summary: Greenlet-aware Python performance profiler, built on yappi.
Home-page: http://github.com/ajdavis/GreenletProfiler/
Author: A. Jesse Jiryu Davis
Author-email: jesse@emptysquare.net
License: http://www.apache.org/licenses/LICENSE-2.0
Keywords: greenlet gevent profiler asynchronous
Platform: UNKNOWN
Classifier: Intended Audience :: Developers
Classifier: License :: OSI Approved :: MIT License
Classifier: Development Status :: 1 - Planning
Classifier: Natural Language :: English
Classifier: Programming Language :: Python :: 2
Classifier: Programming Language :: Python :: 2.6
Classifier: Programming Language :: Python :: 2.7
Classifier: Programming Language :: Python :: 3
Classifier: Programming Language :: Python :: 3.2
Classifier: Programming Language :: Python :: 3.3
Classifier: Operating System :: MacOS :: MacOS X
Classifier: Operating System :: Unix
Classifier: Programming Language :: Python
Classifier: Programming Language :: Python :: Implementation :: CPython
